starlite_react/__init__.py
starlite_react/controller.py
starlite_react/py.typed
starlite_react-0.1.1.dist-info/entry_points.txt
starlite_react-0.1.1.dist-info/LICENSE
starlite_react-0.1.1.dist-info/WHEEL
starlite_react-0.1.1.dist-info/METADATA
starlite_react-0.1.1.dist-info/RECORD
